netbox_circuitmaintenance/__init__.py
netbox_circuitmaintenance/filtersets.py
netbox_circuitmaintenance/forms.py
netbox_circuitmaintenance/models.py
netbox_circuitmaintenance/navigation.py
netbox_circuitmaintenance/tables.py
netbox_circuitmaintenance/template_content.py
netbox_circuitmaintenance/urls.py
netbox_circuitmaintenance/views.py
netbox_circuitmaintenance/widgets.py
netbox_circuitmaintenance/api/serializers.py
netbox_circuitmaintenance/api/urls.py
netbox_circuitmaintenance/api/views.py
netbox_circuitmaintenance/migrations/0001_squashed_0005_alter_circuitmaintenance_options.py
netbox_circuitmaintenance/migrations/0006_circuitmaintenancenotifications_email_body_and_more.py
netbox_circuitmaintenance/migrations/0007_alter_circuitmaintenancenotifications_options_and_more.py
netbox_circuitmaintenance/migrations/__init__.py
netbox_circuitmaintenance/templates/netbox_circuitmaintenance/calendar.html
netbox_circuitmaintenance/templates/netbox_circuitmaintenance/calendar_widget.html
netbox_circuitmaintenance/templates/netbox_circuitmaintenance/circuitmaintenance.html
netbox_circuitmaintenance/templates/netbox_circuitmaintenance/circuitmaintenance_include.html
netbox_circuitmaintenance/templates/netbox_circuitmaintenance/circuitmaintenancenotifications.html
netbox_circuitmaintenance/templates/netbox_circuitmaintenance/providermaintenance_include.html
netbox_circuitmaintenance/templates/netbox_circuitmaintenance/widget.html
netbox_circuitmaintenance-0.6.0.dist-info/licenses/LICENSE
netbox_circuitmaintenance-0.6.0.dist-info/METADATA
netbox_circuitmaintenance-0.6.0.dist-info/WHEEL
netbox_circuitmaintenance-0.6.0.dist-info/top_level.txt
netbox_circuitmaintenance-0.6.0.dist-info/RECORD
