Metadata-Version: 2.4
Name: netbox-circuitmaintenance
Version: 0.6.0
Summary: Provides the ability to record circuit maintenance, maintenance impact and maintenance notifications in Netbox and link them to Providers and Circuits.
Author-email: Jason Yates <me@jasonyates.co.uk>
Project-URL: Homepage, https://github.com/jasonyates/netbox-circuitmaintenance
Project-URL: Documentation, https://jasonyates.github.io/netbox-circuitmaintenance
Project-URL: Source, https://github.com/jasonyates/netbox-circuitmaintenance
Project-URL: Tracker, https://github.com/jasonyates/netbox-circuitmaintenance/issues
Keywords: netbox_circuitmaintenance
Classifier: Development Status :: 2 - Pre-Alpha
Classifier: Intended Audience :: Developers
Classifier: Natural Language :: English
Classifier: Programming Language :: Python :: 3
Classifier: Programming Language :: Python :: 3.10
Classifier: Programming Language :: Python :: 3.11
Classifier: Programming Language :: Python :: 3.12
Requires-Python: >=3.10.0
License-File: LICENSE
Provides-Extra: dev
Requires-Dist: black==25.1.0; extra == "dev"
Requires-Dist: bumpver; extra == "dev"
Requires-Dist: isort==6.0.1; extra == "dev"
Requires-Dist: pip-tools; extra == "dev"
Requires-Dist: pytest; extra == "dev"
Requires-Dist: flake8==7.2.0; extra == "dev"
Requires-Dist: pyproject-flake8==7.0.0; extra == "dev"
Requires-Dist: twine==6.1.0; extra == "dev"
Requires-Dist: Sphinx==8.2.3; extra == "dev"
Requires-Dist: watchdog==6.0.0; extra == "dev"
Dynamic: license-file
